{"name":"Login Successful","id":"login-module;login-successful","testSteps":[{"number":1,"description":"Given that the user is on the page","duration":21887,"startTime":"2022-08-31T14:14:59.962166400-05:00[America/Bogota]","screenshots":[{"screenshot":"60a01b4e58e23ddfc9ae2e81d2bfa6e6aa53022ccbca81866cad5cf1805b03a0.png","timeStamp":1661973321849}],"result":"SUCCESS","precondition":false,"level":0,"children":[{"number":2,"description":"Tatiana opens the https://www.bon-bonite.com/","duration":21674,"startTime":"2022-08-31T14:15:00.163627700-05:00[America/Bogota]","screenshots":[{"screenshot":"60a01b4e58e23ddfc9ae2e81d2bfa6e6aa53022ccbca81866cad5cf1805b03a0.png","timeStamp":1661973321837}],"result":"SUCCESS","precondition":false,"level":1}]},{"number":3,"description":"When he enter his credentials correctly\r\n| cedula | password |\r\n| 1014856939 | g.8uw69JywvUmM2 |","duration":8679,"startTime":"2022-08-31T14:15:21.851921900-05:00[America/Bogota]","screenshots":[{"screenshot":"b4a05b78c40e9fbdb15cc17459ec71c0ed7a4fe96215e2397cbd6147f0799d11.png","timeStamp":1661973330531}],"result":"SUCCESS","precondition":false,"level":0,"children":[{"number":4,"description":"Tatiana login","duration":8651,"startTime":"2022-08-31T14:15:21.873863600-05:00[America/Bogota]","screenshots":[{"screenshot":"b4a05b78c40e9fbdb15cc17459ec71c0ed7a4fe96215e2397cbd6147f0799d11.png","timeStamp":1661973330525}],"result":"SUCCESS","precondition":false,"level":1,"children":[{"number":5,"description":"Tatiana clicks on Click in button account in the index","duration":2694,"startTime":"2022-08-31T14:15:21.888852-05:00[America/Bogota]","screenshots":[{"screenshot":"e9e40a7bc91f922a4cc61f5c86fbee6ee4047760298b827ea0f9e422a58dd09e.png","timeStamp":1661973322509},{"screenshot":"7b5032877ad3bcb826874fd73b674b25dd3fc49348a7dcfc0f3404b98a073c83.png","timeStamp":1661973324583}],"result":"SUCCESS","precondition":false,"level":2},{"number":6,"description":"Tatiana waits the Enter your document for login until be Enabled","duration":261,"startTime":"2022-08-31T14:15:24.589370700-05:00[America/Bogota]","screenshots":[{"screenshot":"7b5032877ad3bcb826874fd73b674b25dd3fc49348a7dcfc0f3404b98a073c83.png","timeStamp":1661973324595},{"screenshot":"795e567f8e995c3e7a8060a9942b9259c34466368a3109520d43045e891c3381.png","timeStamp":1661973324850}],"result":"SUCCESS","precondition":false,"level":2},{"number":7,"description":"Tatiana enters \u00271014856939\u0027 into Enter your document for login","duration":373,"startTime":"2022-08-31T14:15:24.855658900-05:00[America/Bogota]","screenshots":[{"screenshot":"795e567f8e995c3e7a8060a9942b9259c34466368a3109520d43045e891c3381.png","timeStamp":1661973324861},{"screenshot":"ac64f31719cd64e4bd96e712614b7363a51419cb0f134e9fb5a183e2e44eec9a.png","timeStamp":1661973325229}],"result":"SUCCESS","precondition":false,"level":2},{"number":8,"description":"Tatiana enters \u0027g.8uw69JywvUmM2\u0027 into Enter your password for login","duration":362,"startTime":"2022-08-31T14:15:25.231161800-05:00[America/Bogota]","screenshots":[{"screenshot":"ac64f31719cd64e4bd96e712614b7363a51419cb0f134e9fb5a183e2e44eec9a.png","timeStamp":1661973325237},{"screenshot":"875f75125601cb627e348021fa4ff43b4a3fd45ebaf1c20c40ceab5818d5e1fe.png","timeStamp":1661973325593}],"result":"SUCCESS","precondition":false,"level":2},{"number":9,"description":"Tatiana waits the Click in login until be Enabled","duration":183,"startTime":"2022-08-31T14:15:25.596235100-05:00[America/Bogota]","screenshots":[{"screenshot":"875f75125601cb627e348021fa4ff43b4a3fd45ebaf1c20c40ceab5818d5e1fe.png","timeStamp":1661973325601},{"screenshot":"875f75125601cb627e348021fa4ff43b4a3fd45ebaf1c20c40ceab5818d5e1fe.png","timeStamp":1661973325779}],"result":"SUCCESS","precondition":false,"level":2},{"number":10,"description":"Tatiana clicks on Click in login","duration":4737,"startTime":"2022-08-31T14:15:25.781329500-05:00[America/Bogota]","screenshots":[{"screenshot":"875f75125601cb627e348021fa4ff43b4a3fd45ebaf1c20c40ceab5818d5e1fe.png","timeStamp":1661973325787},{"screenshot":"b4a05b78c40e9fbdb15cc17459ec71c0ed7a4fe96215e2397cbd6147f0799d11.png","timeStamp":1661973330518}],"result":"SUCCESS","precondition":false,"level":2}]}]},{"number":11,"description":"Then the user will be logged in","duration":2233,"startTime":"2022-08-31T14:15:30.531683900-05:00[America/Bogota]","screenshots":[{"screenshot":"8175bdfa8f97676b6a1f0f4253adf4936622efffab6be6e8bcbba06cdef68570.png","timeStamp":1661973332764}],"result":"SUCCESS","precondition":false,"level":0,"children":[{"number":12,"description":"Then compare hello should be \u0027Hola 1014856939 (\u0026iquest;no eres 1014856939? Cerrar sesi\u0026oacute;n)\u0027","duration":155,"startTime":"2022-08-31T14:15:32.604257600-05:00[America/Bogota]","screenshots":[{"screenshot":"8175bdfa8f97676b6a1f0f4253adf4936622efffab6be6e8bcbba06cdef68570.png","timeStamp":1661973332716},{"screenshot":"8175bdfa8f97676b6a1f0f4253adf4936622efffab6be6e8bcbba06cdef68570.png","timeStamp":1661973332759}],"result":"SUCCESS","precondition":false,"level":1}]}],"userStory":{"id":"login-module","storyName":"Login module","path":"src/test/resources/features/login.feature","narrative":"  as a user\n  you want to login on the page\n  with your credentials\n  to enter make a purchase","type":"feature"},"featureTag":{"name":"Features/Login module","type":"feature","displayName":"Features/Login module"},"title":"Login Successful","tags":[{"name":"Login module","type":"feature","displayName":"Login module"}],"startTime":"2022-08-31T14:14:59.845449200-05:00[America/Bogota]","duration":32920,"projectKey":"","sessionId":"ba61dc8bdc5a57e84b4b754c6feec271","driver":"chrome","isManualTestingUpToDate":false,"manual":false,"testSource":"Cucumber","actors":[{"name":"Tatiana","can":["browse the web"]}],"result":"SUCCESS"}